{"platforms": [{"name": "치지직", "viewers": 4988, "channels": 169, "link": "https://chzzk.naver.com"}], "categories": [{"game": "게임", "viewers": 970, "channels": 20}, {"game": "롤", "viewers": 339, "channels": 20}, {"game": "발로란트", "viewers": 123, "channels": 20}, {"game": "오버워치", "viewers": 191, "channels": 20}, {"game": "배틀그라운드", "viewers": 153, "channels": 20}, {"game": "마인크래프트", "viewers": 159, "channels": 20}, {"game": "서든어택", "viewers": 13, "channels": 7}, {"game": "로스트아크", "viewers": 2293, "channels": 20}, {"game": "FC온라인", "viewers": 58, "channels": 14}, {"game": "스타크래프트", "viewers": 689, "channels": 8}], "streamers": [{"name": "도읍지", "viewers": 681, "category": "로스트아크", "title": "3시 로스피 본캐대결", "platform": "치지직", "link": "https://chzzk.naver.com/live/20118453"}, {"name": "쫀지", "viewers": 595, "category": "로스트아크", "title": "역대급 밸패    로스트아크  쫀지", "platform": "치지직", "link": "https://chzzk.naver.com/live/20117975"}, {"name": "쿠온 레이 Planeta", "viewers": 536, "category": "스타크래프트", "title": "승달님 손목꺾기", "platform": "치지직", "link": "https://chzzk.naver.com/live/20120024"}, {"name": "게임하는인기", "viewers": 459, "category": "로스트아크", "title": "밸런스 패치 보다가 오후3시 로스피 출격 (고정댓글) [로스트아크]", "platform": "치지직", "link": "https://chzzk.naver.com/live/20119774"}, {"name": "리연 L", "viewers": 415, "category": "로스트아크", "title": "리퍼연구소", "platform": "치지직", "link": "https://chzzk.naver.com/live/20118161"}, {"name": "두니주니", "viewers": 409, "category": "게임", "title": "EWC 그룹스테이지 2일차 5시 시작 한국팀 비상상상상", "platform": "치지직", "link": "https://chzzk.naver.com/live/20122432"}, {"name": "재슥짱1", "viewers": 183, "category": "롤", "title": "롤악귀 %$@%#$#들아!!!", "platform": "치지직", "link": "https://chzzk.naver.com/live/20117610"}, {"name": "곰캐", "viewers": 150, "category": "게임", "title": "현직 PD와 함께보는 명조 4장 2막🎧", "platform": "치지직", "link": "https://chzzk.naver.com/live/20122651"}, {"name": "EWC 공식 채널B", "viewers": 129, "category": "게임", "title": "WBG vs GodL - VSN vs FW | 그룹 2일차 | TFT |", "platform": "치지직", "link": "https://chzzk.naver.com/live/20122954"}, {"name": "박진규02", "viewers": 99, "category": "오버워치", "title": "2주 노방종 시작 티어 올릴게요 ㅋ", "platform": "치지직", "link": "https://chzzk.naver.com/live/20118080"}, {"name": "김주선", "viewers": 94, "category": "게임", "title": "아침의 행복 명조 방송 반갑습니다\n", "platform": "치지직", "link": "https://chzzk.naver.com/live/20117840"}, {"name": "텔론", "viewers": 75, "category": "롤", "title": "클래식 롤 프로게이머가 될게요", "platform": "치지직", "link": "https://chzzk.naver.com/live/20119639"}, {"name": "왓구홍길동", "viewers": 75, "category": "배틀그라운드", "title": "경쟁전 서바이버 6000점 찍기 4일차", "platform": "치지직", "link": "https://chzzk.naver.com/live/20119913"}, {"name": "주혀미", "viewers": 72, "category": "스타크래프트", "title": "[훈수환영] 스아가 4일차 저그 캠페인 이어서 해보겠습니다 ~ ", "platform": "치지직", "link": "https://chzzk.naver.com/live/20118349"}, {"name": "푸후", "viewers": 70, "category": "게임", "title": "명조 띵콘 콘서트  같이보기!- / 발캠 07/29", "platform": "치지직", "link": "https://chzzk.naver.com/live/20120526"}, {"name": "단시하", "viewers": 40, "category": "발로란트", "title": "폐관수련해서 불멸가기 1일차", "platform": "치지직", "link": "https://chzzk.naver.com/live/20118531"}, {"name": "새벽냥", "viewers": 35, "category": "발로란트", "title": "너무 잠와서 조금만 ฅ^•ﻌ•^ฅ", "platform": "치지직", "link": "https://chzzk.naver.com/live/20118712"}, {"name": "강결", "viewers": 35, "category": "로스트아크", "title": "로스트아크 오랜만!! 깜짝 밸패 뭔가요?", "platform": "치지직", "link": "https://chzzk.naver.com/live/20120332"}, {"name": "잠옷고양이", "viewers": 33, "category": "마인크래프트", "title": "실친서버 야생", "platform": "치지직", "link": "https://chzzk.naver.com/live/20120431"}, {"name": "카오스조커", "viewers": 33, "category": "스타크래프트", "title": "공허의 유산 로그라이크 3회차 ", "platform": "치지직", "link": "https://chzzk.naver.com/live/20119843"}, {"name": "서민채", "viewers": 29, "category": "게임", "title": "롤체신입5일차) 오랜만입니다....오랜만맞나 ?", "platform": "치지직", "link": "https://chzzk.naver.com/live/20122232"}, {"name": "양거북", "viewers": 28, "category": "스타크래프트", "title": "「치지직 양영호」 굳데이 커맨더", "platform": "치지직", "link": "https://chzzk.naver.com/live/20120064"}, {"name": "난몰라1", "viewers": 22, "category": "게임", "title": "1409점 싫지만 생각나는... 롤체입니다", "platform": "치지직", "link": "https://chzzk.naver.com/live/20119428"}, {"name": "보듬", "viewers": 22, "category": "배틀그라운드", "title": "한낮 경쟁배그🧡", "platform": "치지직", "link": "https://chzzk.naver.com/live/20119688"}, {"name": "이청멍", "viewers": 22, "category": "로스트아크", "title": "황제는 죽었다 (얼마나 죽었는지 알아보기)  /  온 세상이 로스트아크 ", "platform": "치지직", "link": "https://chzzk.naver.com/live/20119674"}, {"name": "만만수o", "viewers": 21, "category": "롤", "title": "[롤 5:5 내전] 내전 가보자잇", "platform": "치지직", "link": "https://chzzk.naver.com/live/20121051"}, {"name": "에루인데요", "viewers": 20, "category": "오버워치", "title": "오버워치 수다방 탐방", "platform": "치지직", "link": "https://chzzk.naver.com/live/20120517"}, {"name": "백도화님", "viewers": 19, "category": "롤", "title": "롤대녀 등쟝", "platform": "치지직", "link": "https://chzzk.naver.com/live/20122397"}, {"name": "야린아", "viewers": 16, "category": "마인크래프트", "title": "마크 힐링 야생 서버 (시참)~~", "platform": "치지직", "link": "https://chzzk.naver.com/live/20120693"}, {"name": "오일오", "viewers": 16, "category": "로스트아크", "title": "다시 또 로요일 ι(˙◁˙ )/ 죽습>두동 세팅하고 레이드가기", "platform": "치지직", "link": "https://chzzk.naver.com/live/20118678"}, {"name": "청남방TV", "viewers": 13, "category": "로스트아크", "title": "[로스트아크] 로요일", "platform": "치지직", "link": "https://chzzk.naver.com/live/20118778"}, {"name": "페잣", "viewers": 13, "category": "로스트아크", "title": "로요일 패치내역 살피고 주간 숙제(천상+지옥+할모시) 미리 해놓기!", "platform": "치지직", "link": "https://chzzk.naver.com/live/20118265"}, {"name": "꼐속", "viewers": 12, "category": "게임", "title": "c1160 8시 마빵단의 왕관", "platform": "치지직", "link": "https://chzzk.naver.com/live/20119816"}, {"name": "EWC 공식 채널C", "viewers": 12, "category": "게임", "title": "[EN/SUB] WBG vs GodL - VSN vs FW | 그룹 2일", "platform": "치지직", "link": "https://chzzk.naver.com/live/20122773"}, {"name": "신노스케입니다", "viewers": 12, "category": "오버워치", "title": "탱딜 폐관수련", "platform": "치지직", "link": "https://chzzk.naver.com/live/20116686"}, {"name": "소오올빈", "viewers": 12, "category": "마인크래프트", "title": "🍀반야생 ｜ 경제 · 건축 · 소통🍀[마인크래프트 시참] ", "platform": "치지직", "link": "https://chzzk.naver.com/live/20122519"}, {"name": "군침쿤", "viewers": 11, "category": "게임", "title": "띵조 상담/대리(엔컨만슛) 😊😊😁 !sr 노래신청", "platform": "치지직", "link": "https://chzzk.naver.com/live/20121157"}, {"name": "달래곤", "viewers": 11, "category": "마인크래프트", "title": "[마인밸리] 오늘은 농장을 좀 손볼거에용", "platform": "치지직", "link": "https://chzzk.naver.com/live/20119549"}, {"name": "정카임", "viewers": 10, "category": "배틀그라운드", "title": "[배틀그라운드] 배그 낮뱅 깔짝..(w.백루루) (시참x) *진짜 배린이", "platform": "치지직", "link": "https://chzzk.naver.com/live/20120486"}, {"name": "타마고 아치", "viewers": 10, "category": "로스트아크", "title": "쿠폰) 무신사와함께하는로생한컷", "platform": "치지직", "link": "https://chzzk.naver.com/live/20118264"}, {"name": "도 누", "viewers": 10, "category": "FC온라인", "title": "무료로 어쩌고 저쩌고 ", "platform": "치지직", "link": "https://chzzk.naver.com/live/20122595"}, {"name": "C1 Karen", "viewers": 9, "category": "롤", "title": "C1카렌 / 배치부터 챌까지미션,투챌가즈앗 / 롤재판O / 강의,관피o", "platform": "치지직", "link": "https://chzzk.naver.com/live/19993879"}, {"name": "잼밍서", "viewers": 9, "category": "발로란트", "title": "발로란트 하면서 수다 떨어요 ㅎㅅㅎ (시참 가능)", "platform": "치지직", "link": "https://chzzk.naver.com/live/20122107"}, {"name": "신 S1N", "viewers": 9, "category": "오버워치", "title": "같이 오버워치 배울 사람?", "platform": "치지직", "link": "https://chzzk.naver.com/live/20120004"}, {"name": "백 루 루", "viewers": 9, "category": "배틀그라운드", "title": "🎬또또또또비와!!우아!!!!미쳤나봐!(W.정카임。데스티니ＮＢ)💙유입_환영", "platform": "치지직", "link": "https://chzzk.naver.com/live/20119223"}, {"name": "단하님", "viewers": 9, "category": "배틀그라운드", "title": "0722 - 맞팔환영 -   🌱  -  1팰월드  2배그", "platform": "치지직", "link": "https://chzzk.naver.com/live/20119882"}, {"name": "빵짱", "viewers": 9, "category": "마인크래프트", "title": "쿨돌아온 마크 하드코어런 3클째 도전  ㄱ", "platform": "치지직", "link": "https://chzzk.naver.com/live/20117925"}, {"name": "랜드홀", "viewers": 9, "category": "로스트아크", "title": "음머어어 음머음머 ( 해석 : 나르카 지평 3단계 갔다가 재료 먹으러 가", "platform": "치지직", "link": "https://chzzk.naver.com/live/20120968"}, {"name": "슬이의 게임 일기", "viewers": 9, "category": "스타크래프트", "title": "(시참O)이번주 돌변 난이도 실화예요??", "platform": "치지직", "link": "https://chzzk.naver.com/live/20122619"}, {"name": "컨텐츠도와주는형", "viewers": 8, "category": "게임", "title": "점복데이(롤체 59일차)", "platform": "치지직", "link": "https://chzzk.naver.com/live/20121484"}], "fetched": "2026-07-22T17:00:09"}