{"platforms": [{"name": "치지직", "viewers": 7237, "channels": 164, "link": "https://chzzk.naver.com"}], "categories": [{"game": "게임", "viewers": 932, "channels": 20}, {"game": "롤", "viewers": 790, "channels": 20}, {"game": "발로란트", "viewers": 310, "channels": 20}, {"game": "오버워치", "viewers": 276, "channels": 20}, {"game": "배틀그라운드", "viewers": 344, "channels": 20}, {"game": "마인크래프트", "viewers": 261, "channels": 20}, {"game": "서든어택", "viewers": 7, "channels": 7}, {"game": "로스트아크", "viewers": 4220, "channels": 20}, {"game": "FC온라인", "viewers": 53, "channels": 9}, {"game": "스타크래프트", "viewers": 44, "channels": 8}], "streamers": [{"name": "초승달", "viewers": 2672, "category": "로스트아크", "title": "로아스토리 엔딩 보자~ 카제로스 2막부터!", "platform": "치지직", "link": "https://chzzk.naver.com/live/20101825"}, {"name": "쫀지", "viewers": 1145, "category": "로스트아크", "title": "로아 이대로 괜찮은가? 한번 보겠습니다 로스트아크  쫀지", "platform": "치지직", "link": "https://chzzk.naver.com/live/20102096"}, {"name": "팔차선8", "viewers": 707, "category": "게임", "title": "멸망한 세계에서 살아남는 법", "platform": "치지직", "link": "https://chzzk.naver.com/live/20102596"}, {"name": "복 찌 니", "viewers": 520, "category": "롤", "title": "롤 1일차 치수 욕참기 1일차 치지직  16일차 ❤ ", "platform": "치지직", "link": "https://chzzk.naver.com/live/20103247"}, {"name": "버니버니", "viewers": 241, "category": "발로란트", "title": "레디언트 신입 남캠 4일차 입니다", "platform": "치지직", "link": "https://chzzk.naver.com/live/20101292"}, {"name": "재슥짱1", "viewers": 180, "category": "롤", "title": "롤악귀 %$@%#$#들아!!!", "platform": "치지직", "link": "https://chzzk.naver.com/live/20102177"}, {"name": "VG신선한망치", "viewers": 180, "category": "로스트아크", "title": "모코코트라이 끝! 남은 숙제 털기", "platform": "치지직", "link": "https://chzzk.naver.com/live/20101328"}, {"name": "찬우정", "viewers": 133, "category": "마인크래프트", "title": "마크 하코 엔더런 5시간 컷", "platform": "치지직", "link": "https://chzzk.naver.com/live/20101128"}, {"name": "미르다요", "viewers": 108, "category": "배틀그라운드", "title": "1시 배그 뉴비 알려주기 / 저녁에 오디오 셋팅 받을듯.", "platform": "치지직", "link": "https://chzzk.naver.com/live/20100538"}, {"name": "박진규02", "viewers": 101, "category": "오버워치", "title": "2주 노방종 시작 티어 올릴게요 ㅋ", "platform": "치지직", "link": "https://chzzk.naver.com/live/20098993"}, {"name": "고요o3o", "viewers": 80, "category": "배틀그라운드", "title": "1시 미르다요형님과 배그 강습", "platform": "치지직", "link": "https://chzzk.naver.com/live/20100733"}, {"name": "아로예요", "viewers": 59, "category": "게임", "title": "C 1007) 오랜만이에요 아직 무섭지만 방송도 롤체도 다시 열심히 해볼", "platform": "치지직", "link": "https://chzzk.naver.com/live/20098778"}, {"name": "팡팡에몽", "viewers": 55, "category": "로스트아크", "title": "스타에 재능이 없는 사람", "platform": "치지직", "link": "https://chzzk.naver.com/live/20100750"}, {"name": "EWC 공식 채널B", "viewers": 52, "category": "게임", "title": "WBG vs T1 - ZETA vs JDG | 그룹 1일차 | TFT |", "platform": "치지직", "link": "https://chzzk.naver.com/live/20104576"}, {"name": "프로겐", "viewers": 42, "category": "오버워치", "title": "겐지 조금 잘합니다.", "platform": "치지직", "link": "https://chzzk.naver.com/live/20100582"}, {"name": "달빛머무는밤", "viewers": 40, "category": "로스트아크", "title": "윙꾸", "platform": "치지직", "link": "https://chzzk.naver.com/live/20102413"}, {"name": "EWC 공식 채널C", "viewers": 32, "category": "게임", "title": "[EN/SUB] A조 | 그룹 1일차 | 스트림 A | TFT | EWC", "platform": "치지직", "link": "https://chzzk.naver.com/live/20104315"}, {"name": "야켓", "viewers": 31, "category": "오버워치", "title": "아무거나", "platform": "치지직", "link": "https://chzzk.naver.com/live/20099501"}, {"name": "왓구홍길동", "viewers": 31, "category": "배틀그라운드", "title": "경쟁전 서바이버 6000점 찍기 3일차", "platform": "치지직", "link": "https://chzzk.naver.com/live/20101073"}, {"name": "소희르", "viewers": 30, "category": "로스트아크", "title": "[드롭스] 품질작 하고 고대코어 2개 만듭니다", "platform": "치지직", "link": "https://chzzk.naver.com/live/20102665"}, {"name": "하얀귤", "viewers": 27, "category": "배틀그라운드", "title": "배그 얼른오세요!(미션 사랑♥)", "platform": "치지직", "link": "https://chzzk.naver.com/live/20101334"}, {"name": "만만수o", "viewers": 24, "category": "롤", "title": "[롤 5:5 내전] 내전 가보자 가보자잇", "platform": "치지직", "link": "https://chzzk.naver.com/live/20103303"}, {"name": "미나ㅣMeeNa", "viewers": 24, "category": "오버워치", "title": "오버워치 시네마틱⏱️ 전부 보기!! (feat.뉴비의 시선)", "platform": "치지직", "link": "https://chzzk.naver.com/live/20101925"}, {"name": "튜티", "viewers": 24, "category": "오버워치", "title": "귀염뽀짝 튜티 왔어요 ^ㅁ^", "platform": "치지직", "link": "https://chzzk.naver.com/live/20100376"}, {"name": "EA SPORTS FC온라인", "viewers": 24, "category": "FC온라인", "title": "T1 Navy vs NS Exito | GROUP E DECIDER MA", "platform": "치지직", "link": "https://chzzk.naver.com/live/20104578"}, {"name": "방 문 자", "viewers": 23, "category": "배틀그라운드", "title": "점방문자", "platform": "치지직", "link": "https://chzzk.naver.com/live/20100911"}, {"name": "개순이", "viewers": 22, "category": "마인크래프트", "title": "오늘은 진짜로 엔더드래곤 잡습니다.. ", "platform": "치지직", "link": "https://chzzk.naver.com/live/20101270"}, {"name": "고노바", "viewers": 17, "category": "발로란트", "title": "감시자로 레디가기 DAY 14 역대급 고점", "platform": "치지직", "link": "https://chzzk.naver.com/live/20100896"}, {"name": "꼐속", "viewers": 16, "category": "게임", "title": "c1218 2코 1성으로 9렙을 갈 수 있을 리 없잖아, 무리무리! (※", "platform": "치지직", "link": "https://chzzk.naver.com/live/20101449"}, {"name": "H행구리H", "viewers": 16, "category": "배틀그라운드", "title": "배린이는 배그가 무습다... !시참 시참비는 팔로우!", "platform": "치지직", "link": "https://chzzk.naver.com/live/20100441"}, {"name": "유즈키 나나", "viewers": 15, "category": "마인크래프트", "title": "[냉면서버] 진짜 탈출 하고싶은 사람 ٩( ˙꒳​˙ )ว=͟͟͞ ", "platform": "치지직", "link": "https://chzzk.naver.com/live/20098963"}, {"name": "리네 Renee", "viewers": 14, "category": "오버워치", "title": "[V신입]💕🦫다이아 여정까지! 3포지 1티어씩 👉리플 신청 1+1/듀오권", "platform": "치지직", "link": "https://chzzk.naver.com/live/20102414"}, {"name": "함희루", "viewers": 14, "category": "로스트아크", "title": "모코코상담O/짚톡룰렛 2000) 하늘에 구멍 뚫린듯", "platform": "치지직", "link": "https://chzzk.naver.com/live/20102109"}, {"name": "김연랑", "viewers": 14, "category": "로스트아크", "title": "오늘은..숙제부터 빨리 뺍시다!", "platform": "치지직", "link": "https://chzzk.naver.com/live/20102554"}, {"name": "스피릿 Spirit", "viewers": 14, "category": "스타크래프트", "title": "비가 오듯 .주간돌변 전적이 빨갛게 추적추적.. 협동전", "platform": "치지직", "link": "https://chzzk.naver.com/live/20103258"}, {"name": "노우리", "viewers": 13, "category": "게임", "title": "뭐라고?", "platform": "치지직", "link": "https://chzzk.naver.com/live/20103223"}, {"name": "두부당Dubudang", "viewers": 13, "category": "배틀그라운드", "title": "[팬시참] 두살치두살치!!!!", "platform": "치지직", "link": "https://chzzk.naver.com/live/20101195"}, {"name": "모아이 속상", "viewers": 13, "category": "마인크래프트", "title": "나 아파.....콜록콜록(모아이도박예정)", "platform": "치지직", "link": "https://chzzk.naver.com/live/20103229"}, {"name": "동동영", "viewers": 12, "category": "발로란트", "title": "솔랭 후 시참", "platform": "치지직", "link": "https://chzzk.naver.com/live/20100023"}, {"name": "빨무 로카", "viewers": 12, "category": "스타크래프트", "title": "[로카] 빨무 스타 팀플", "platform": "치지직", "link": "https://chzzk.naver.com/live/20101422"}, {"name": "EWC 공식 채널D", "viewers": 11, "category": "게임", "title": "[EN/SUB] B조 | 그룹 1일차 | 스트림 B | TFT | EWC", "platform": "치지직", "link": "https://chzzk.naver.com/live/20104366"}, {"name": "백모리", "viewers": 11, "category": "마인크래프트", "title": "[냉면서버]진짜 오늘은 냉면 탈탈 털어서 탈출각잡는다고요 API도 없다리", "platform": "치지직", "link": "https://chzzk.naver.com/live/20099373"}, {"name": "랜드홀", "viewers": 11, "category": "로스트아크", "title": "음머어어 음머음머 ( 해석 : 나르카 지평 3단계 갔다가 재료 먹으러 가", "platform": "치지직", "link": "https://chzzk.naver.com/live/20103458"}, {"name": "유다율", "viewers": 11, "category": "로스트아크", "title": "[!이벤트] 모코코는 4막 몰롸..", "platform": "치지직", "link": "https://chzzk.naver.com/live/20100371"}, {"name": "고 담", "viewers": 10, "category": "배틀그라운드", "title": "신입) 초초초 배린이의 배틀그라운드 도전기! (방송14일차)", "platform": "치지직", "link": "https://chzzk.naver.com/live/20101301"}, {"name": "나나뽀", "viewers": 10, "category": "마인크래프트", "title": "[빙고서버] 빠른탈출 ๑˘ꇴ˘๑💜", "platform": "치지직", "link": "https://chzzk.naver.com/live/20101613"}, {"name": "주비냥", "viewers": 10, "category": "로스트아크", "title": "[유입,맞팔환영] 베른 처음가보는 모코코의 ⏱️LOST ARK", "platform": "치지직", "link": "https://chzzk.naver.com/live/20080277"}, {"name": "너가 좀 알려줘", "viewers": 9, "category": "게임", "title": "C1 1105LP 나 뭐 달라진 거 없어???", "platform": "치지직", "link": "https://chzzk.naver.com/live/20101586"}, {"name": "지빙이", "viewers": 9, "category": "배틀그라운드", "title": "오늘인가,, 건방진 꼰펭과의 킬내기", "platform": "치지직", "link": "https://chzzk.naver.com/live/20100506"}, {"name": "응시z", "viewers": 9, "category": "마인크래프트", "title": "[빙고서버] 탈출하고 싶은딩..   #딜 룰렛 맛집", "platform": "치지직", "link": "https://chzzk.naver.com/live/20086436"}], "fetched": "2026-07-21T16:31:05"}