{"platforms": [{"name": "치지직", "viewers": 8525, "channels": 185, "link": "https://chzzk.naver.com"}], "categories": [{"game": "게임", "viewers": 1084, "channels": 20}, {"game": "롤", "viewers": 2417, "channels": 20}, {"game": "발로란트", "viewers": 92, "channels": 19}, {"game": "오버워치", "viewers": 192, "channels": 20}, {"game": "배틀그라운드", "viewers": 122, "channels": 20}, {"game": "마인크래프트", "viewers": 104, "channels": 20}, {"game": "서든어택", "viewers": 28, "channels": 9}, {"game": "로스트아크", "viewers": 4234, "channels": 20}, {"game": "FC온라인", "viewers": 53, "channels": 17}, {"game": "스타크래프트", "viewers": 199, "channels": 20}], "streamers": [{"name": "이 다", "viewers": 2889, "category": "로스트아크", "title": "갑자기 재미있어진 게임", "platform": "치지직", "link": "https://chzzk.naver.com/live/20159828"}, {"name": "소우릎", "viewers": 1432, "category": "롤", "title": "롤 강의 준비", "platform": "치지직", "link": "https://chzzk.naver.com/live/20159248"}, {"name": "캡틴잭", "viewers": 880, "category": "로스트아크", "title": "오후 7시 스펙업을 위한 캡신사/싸인회 엽니다 잘부탁드립니다", "platform": "치지직", "link": "https://chzzk.naver.com/live/20158685"}, {"name": "큐베 CuVee", "viewers": 795, "category": "롤", "title": "소우릎씨 롤알려주다? LCK 3라운드 분석해보기(8시쯤)", "platform": "치지직", "link": "https://chzzk.naver.com/live/20158762"}, {"name": "두니주니", "viewers": 362, "category": "게임", "title": "EWC 8강 농심레드포스 결승까지 가보즈앙", "platform": "치지직", "link": "https://chzzk.naver.com/live/20160195"}, {"name": "EWC 공식 채널B", "viewers": 341, "category": "게임", "title": "VP vs VSN - WBG vs AUR | 8강 | TFT | EWC ", "platform": "치지직", "link": "https://chzzk.naver.com/live/20159792"}, {"name": "박용욱", "viewers": 139, "category": "로스트아크", "title": "디트의 로망 '차붕' 해보겠습니다", "platform": "치지직", "link": "https://chzzk.naver.com/live/20158645"}, {"name": "플레임TV", "viewers": 132, "category": "롤", "title": "오늘은 묵언수행하면서 롤", "platform": "치지직", "link": "https://chzzk.naver.com/live/20161578"}, {"name": "리연 L", "viewers": 118, "category": "로스트아크", "title": "시간 관리자 농가 살리기 222 배율 1.2+", "platform": "치지직", "link": "https://chzzk.naver.com/live/20118161"}, {"name": "미호밍", "viewers": 100, "category": "게임", "title": "과몰입형리액션💖명조 2장 마지막 에필로그 + 2장 후기까지!", "platform": "치지직", "link": "https://chzzk.naver.com/live/20159502"}, {"name": "HaruNuna", "viewers": 80, "category": "로스트아크", "title": "🌱#목소린취향일지도💜#길원모집중 #니나브나는귀엽당", "platform": "치지직", "link": "https://chzzk.naver.com/live/20157182"}, {"name": "인파쓰", "viewers": 62, "category": "게임", "title": "VP vs VSN 세기의 대결 EWC 8강", "platform": "치지직", "link": "https://chzzk.naver.com/live/20160057"}, {"name": "주혀미", "viewers": 50, "category": "스타크래프트", "title": "[훈수환영] 스타응애 프로토스 캠페인 이어서 가보겠습니다 ~", "platform": "치지직", "link": "https://chzzk.naver.com/live/20156292"}, {"name": "나기상", "viewers": 46, "category": "게임", "title": "(광고) 18시 둠스데이 : 라스트 서바이버", "platform": "치지직", "link": "https://chzzk.naver.com/live/20159935"}, {"name": "뮤리벨렌", "viewers": 38, "category": "게임", "title": "명조 2장 8막 할건데 난 3장 언제 가..?", "platform": "치지직", "link": "https://chzzk.naver.com/live/20158313"}, {"name": "Uann 유안", "viewers": 36, "category": "오버워치", "title": "패쫑", "platform": "치지직", "link": "https://chzzk.naver.com/live/20158408"}, {"name": "맹덕엄마", "viewers": 29, "category": "스타크래프트", "title": "1부 스타1vs스타2 중계 2부 RTS 트라이애슬론 vs 레니아워 (w멀", "platform": "치지직", "link": "https://chzzk.naver.com/live/20159972"}, {"name": "코워드", "viewers": 28, "category": "로스트아크", "title": "숙제 전분공개방 데이터수집중", "platform": "치지직", "link": "https://chzzk.naver.com/live/20157562"}, {"name": "딴비딴비", "viewers": 25, "category": "오버워치", "title": "장마가 끝났다구요? 비가 안왔는데요?", "platform": "치지직", "link": "https://chzzk.naver.com/live/20159267"}, {"name": "루태", "viewers": 24, "category": "마인크래프트", "title": "모드 없이 표헌한 현실적인 마인크래프트 생활 체험 맵 하기", "platform": "치지직", "link": "https://chzzk.naver.com/live/20162123"}, {"name": "스타장윤철", "viewers": 24, "category": "스타크래프트", "title": "26년 7월 스타 장윤철", "platform": "치지직", "link": "https://chzzk.naver.com/live/20162404"}, {"name": "호주머니", "viewers": 23, "category": "배틀그라운드", "title": "💜2부 배그하면서 배긁💜", "platform": "치지직", "link": "https://chzzk.naver.com/live/20158266"}, {"name": "달꼼", "viewers": 21, "category": "게임", "title": "₍ᐢ.ˬ.ᐡ₎ 💜🐰💛 그묘일", "platform": "치지직", "link": "https://chzzk.naver.com/live/20160395"}, {"name": "루냐잉", "viewers": 21, "category": "로스트아크", "title": "먘 (ˆ⩌⩊⩌ˆ)੭", "platform": "치지직", "link": "https://chzzk.naver.com/live/20160023"}, {"name": "난몰라1", "viewers": 20, "category": "게임", "title": "1552점 재밌는 롤체", "platform": "치지직", "link": "https://chzzk.naver.com/live/20159688"}, {"name": "유제이와 고양이", "viewers": 20, "category": "오버워치", "title": "2단승급 좀복구했슴 오늘은??.. ★티맞1만★ !시참 !미션", "platform": "치지직", "link": "https://chzzk.naver.com/live/20159204"}, {"name": "박정현임", "viewers": 19, "category": "게임", "title": "명조를 사랑만한 사람 (질문 계정상담 컨탠츠 대신맨 환영)", "platform": "치지직", "link": "https://chzzk.naver.com/live/20157552"}, {"name": "새지", "viewers": 19, "category": "오버워치", "title": "오버워치 2500시간의 개고수 플레이", "platform": "치지직", "link": "https://chzzk.naver.com/live/20158705"}, {"name": "고소리 Gosori", "viewers": 19, "category": "로스트아크", "title": "⚔🪽 발키리랑 친해지기", "platform": "치지직", "link": "https://chzzk.naver.com/live/20158673"}, {"name": "깝도이닷", "viewers": 18, "category": "스타크래프트", "title": "2026.7.24(금) [깝도이] 스타 빨무 팀플 StarCraft", "platform": "치지직", "link": "https://chzzk.naver.com/live/20161728"}, {"name": "챠붕이", "viewers": 17, "category": "오버워치", "title": "(신입) 빠대 시참 마필", "platform": "치지직", "link": "https://chzzk.naver.com/live/20158474"}, {"name": "님님잉", "viewers": 17, "category": "스타크래프트", "title": "스타크래프트 라고 알아요 ? 민속놀이야 이게 ?", "platform": "치지직", "link": "https://chzzk.naver.com/live/20158679"}, {"name": "독학님", "viewers": 16, "category": "발로란트", "title": "[V] 발로란트 초보 실버 경쟁/일반(시참 가능)", "platform": "치지직", "link": "https://chzzk.naver.com/live/20160035"}, {"name": "촉수마왕", "viewers": 16, "category": "스타크래프트", "title": "촉촉해요", "platform": "치지직", "link": "https://chzzk.naver.com/live/20153705"}, {"name": "프리리Freeree", "viewers": 15, "category": "오버워치", "title": "잼민이 말고 학생들은 대환영이야", "platform": "치지직", "link": "https://chzzk.naver.com/live/20157970"}, {"name": "G스토리1", "viewers": 14, "category": "게임", "title": "7시 명조 상담 2부 주간 숙제", "platform": "치지직", "link": "https://chzzk.naver.com/live/20161591"}, {"name": "틈히", "viewers": 14, "category": "마인크래프트", "title": "흑요석 감옥 그만! 리필 그만!!!!!! 그만 캐고 싶어ㅓㅓㅓㅓ!!! 일", "platform": "치지직", "link": "https://chzzk.naver.com/live/20157344"}, {"name": "미리센세", "viewers": 13, "category": "게임", "title": "[픽업 상담] 뭐 뽑을지 고민되죠? 너만의 정답을 찾아줄게! (feat.", "platform": "치지직", "link": "https://chzzk.naver.com/live/20159679"}, {"name": "차원랑", "viewers": 13, "category": "게임", "title": "[신입] 명조 2막 시작 (🌼❛ ֊ ❛„)", "platform": "치지직", "link": "https://chzzk.naver.com/live/20160038"}, {"name": "민므다요", "viewers": 13, "category": "배틀그라운드", "title": "[!노방종] 노방종 5일차인데 왜 6일 남아찌..?", "platform": "치지직", "link": "https://chzzk.naver.com/live/20152588"}, {"name": "해찬 HAECHAN", "viewers": 13, "category": "배틀그라운드", "title": "배그 오늘은 치킨묵자...시참o 유입o", "platform": "치지직", "link": "https://chzzk.naver.com/live/20156654"}, {"name": "별도림", "viewers": 13, "category": "스타크래프트", "title": "녹아버려따..", "platform": "치지직", "link": "https://chzzk.naver.com/live/20160610"}, {"name": "광무리", "viewers": 12, "category": "오버워치", "title": "즐거운 금요일 되시길 바랍니다리미", "platform": "치지직", "link": "https://chzzk.naver.com/live/20157282"}, {"name": "신해조", "viewers": 12, "category": "서든어택", "title": "[지존🐉] 오늘 그마 갑니다. 부캐 백호탁구도 뽑자!", "platform": "치지직", "link": "https://chzzk.naver.com/live/20160359"}, {"name": "오락교", "viewers": 12, "category": "로스트아크", "title": "즐겜 유부남의 로스트아크♬ 질문, 상담 환영합니다~", "platform": "치지직", "link": "https://chzzk.naver.com/live/20159694"}, {"name": "겜빡이존", "viewers": 12, "category": "로스트아크", "title": "[ 뉴비&복귀 환영 1:1 맞춤 ]갈망에 살고 갈망에 죽는다! 갈!! 말", "platform": "치지직", "link": "https://chzzk.naver.com/live/20154487"}, {"name": "피츠콜리", "viewers": 11, "category": "발로란트", "title": "실딱이의 다이아를 향한 여정 탐험기", "platform": "치지직", "link": "https://chzzk.naver.com/live/20157403"}, {"name": "찬울 Chanwool", "viewers": 11, "category": "오버워치", "title": "[BB크림] 후기", "platform": "치지직", "link": "https://chzzk.naver.com/live/20158855"}, {"name": "박견우", "viewers": 11, "category": "로스트아크", "title": "반갑습니다", "platform": "치지직", "link": "https://chzzk.naver.com/live/20159815"}, {"name": "노가노", "viewers": 11, "category": "FC온라인", "title": "불금도 달리는 개 쳐 갓 겜", "platform": "치지직", "link": "https://chzzk.naver.com/live/20162121"}], "fetched": "2026-07-24T19:27:29"}