{
  "platforms": [
    {
      "name": "치지직",
      "viewers": "0명",
      "channels": "163 채널",
      "peak": "0명",
      "link": "https://chzzk.naver.com/live"
    }
  ],
  "categories": [
    {
      "rank": 1,
      "game": "게임",
      "viewers": "0명",
      "channels": "20 채널"
    },
    {
      "rank": 2,
      "game": "리그오브레전드",
      "viewers": "0명",
      "channels": "20 채널"
    },
    {
      "rank": 3,
      "game": "발로란트",
      "viewers": "0명",
      "channels": "20 채널"
    },
    {
      "rank": 4,
      "game": "배틀그라운드",
      "viewers": "0명",
      "channels": "20 채널"
    },
    {
      "rank": 5,
      "game": "팰월드",
      "viewers": "0명",
      "channels": "20 채널"
    },
    {
      "rank": 6,
      "game": "마인크래프트",
      "viewers": "0명",
      "channels": "20 채널"
    },
    {
      "rank": 7,
      "game": "서든어택",
      "viewers": "0명",
      "channels": "6 채널"
    },
    {
      "rank": 8,
      "game": "스타크래프트",
      "viewers": "0명",
      "channels": "19 채널"
    },
    {
      "rank": 9,
      "game": "FC온라인",
      "viewers": "0명",
      "channels": "18 채널"
    }
  ],
  "streamers": [
    {
      "rank": 1,
      "name": "김태1빈",
      "viewers": "0",
      "category": "게임",
      "url": ""
    },
    {
      "rank": 2,
      "name": "꼐속",
      "viewers": "0",
      "category": "게임",
      "url": ""
    },
    {
      "rank": 3,
      "name": "김무강1",
      "viewers": "0",
      "category": "게임",
      "url": ""
    },
    {
      "rank": 4,
      "name": "두니주니",
      "viewers": "0",
      "category": "게임",
      "url": ""
    },
    {
      "rank": 5,
      "name": "EWC 공식 채널B",
      "viewers": "0",
      "category": "게임",
      "url": ""
    },
    {
      "rank": 6,
      "name": "을 동",
      "viewers": "0",
      "category": "게임",
      "url": ""
    },
    {
      "rank": 7,
      "name": "팔차선8",
      "viewers": "0",
      "category": "게임",
      "url": ""
    },
    {
      "rank": 8,
      "name": "인파쓰",
      "viewers": "0",
      "category": "게임",
      "url": ""
    },
    {
      "rank": 9,
      "name": "1Chon",
      "viewers": "0",
      "category": "게임",
      "url": ""
    },
    {
      "rank": 10,
      "name": "문카블입니다",
      "viewers": "0",
      "category": "게임",
      "url": ""
    },
    {
      "rank": 11,
      "name": "악동 르윈",
      "viewers": "0",
      "category": "게임",
      "url": ""
    },
    {
      "rank": 12,
      "name": "난몰라1",
      "viewers": "0",
      "category": "게임",
      "url": ""
    },
    {
      "rank": 13,
      "name": "나는벌레덩",
      "viewers": "0",
      "category": "게임",
      "url": ""
    },
    {
      "rank": 14,
      "name": "흐쟁이",
      "viewers": "0",
      "category": "게임",
      "url": ""
    },
    {
      "rank": 15,
      "name": "카리나쨩",
      "viewers": "0",
      "category": "게임",
      "url": ""
    },
    {
      "rank": 16,
      "name": "강등탈",
      "viewers": "0",
      "category": "게임",
      "url": ""
    },
    {
      "rank": 17,
      "name": "왱이",
      "viewers": "0",
      "category": "게임",
      "url": ""
    },
    {
      "rank": 18,
      "name": "다정현",
      "viewers": "0",
      "category": "게임",
      "url": ""
    },
    {
      "rank": 19,
      "name": "매드라이프 MadLife",
      "viewers": "0",
      "category": "게임",
      "url": ""
    },
    {
      "rank": 20,
      "name": "고뇽찌",
      "viewers": "0",
      "category": "게임",
      "url": ""
    }
  ],
  "fetched": "2026-07-23T18:53:40.154587"
}