{
  "platforms": [
    {
      "rank": 1,
      "name": "SOOP",
      "viewers": "99920",
      "channels": "2005",
      "link": "https://www.sooplive.com"
    },
    {
      "rank": 2,
      "name": "치지직",
      "viewers": "87282",
      "channels": "2399",
      "link": "https://chzzk.naver.com"
    },
    {
      "rank": 3,
      "name": "트위치",
      "viewers": "2769",
      "channels": "94",
      "link": "https://www.twitch.tv"
    },
    {
      "rank": 4,
      "name": "씨미",
      "viewers": "527",
      "channels": "28",
      "link": "https://seemi.live"
    }
  ],
  "fetched": "2026-07-24T16:36:31.810620",
  "streamers": [
    {
      "rank": 1,
      "name": "강지",
      "viewers": "11124",
      "platform": "SOOP",
      "link": ""
    },
    {
      "rank": 2,
      "name": "오아",
      "viewers": "5405",
      "platform": "SOOP",
      "link": ""
    },
    {
      "rank": 3,
      "name": "서도일",
      "viewers": "4621",
      "platform": "SOOP",
      "link": ""
    },
    {
      "rank": 4,
      "name": "정중만",
      "viewers": "4170",
      "platform": "SOOP",
      "link": ""
    },
    {
      "rank": 5,
      "name": "파카",
      "viewers": "4108",
      "platform": "SOOP",
      "link": ""
    },
    {
      "rank": 6,
      "name": "두치와뿌꾸",
      "viewers": "3185",
      "platform": "SOOP",
      "link": ""
    },
    {
      "rank": 7,
      "name": "강소연",
      "viewers": "3068",
      "platform": "SOOP",
      "link": ""
    },
    {
      "rank": 8,
      "name": "단츄♪",
      "viewers": "2452",
      "platform": "SOOP",
      "link": ""
    },
    {
      "rank": 9,
      "name": "조강현 그리고 스틸로",
      "viewers": "2430",
      "platform": "SOOP",
      "link": ""
    },
    {
      "rank": 10,
      "name": "둥그레",
      "viewers": "2381",
      "platform": "SOOP",
      "link": ""
    },
    {
      "rank": 11,
      "name": "s시조새s",
      "viewers": "2096",
      "platform": "SOOP",
      "link": ""
    },
    {
      "rank": 12,
      "name": "김도의 취미방송",
      "viewers": "2090",
      "platform": "SOOP",
      "link": ""
    },
    {
      "rank": 13,
      "name": "Best도재욱",
      "viewers": "2051",
      "platform": "SOOP",
      "link": ""
    },
    {
      "rank": 14,
      "name": "수이,",
      "viewers": "1808",
      "platform": "SOOP",
      "link": ""
    },
    {
      "rank": 15,
      "name": "쌍베",
      "viewers": "1788",
      "platform": "SOOP",
      "link": ""
    },
    {
      "rank": 16,
      "name": "레고77",
      "viewers": "1723",
      "platform": "SOOP",
      "link": ""
    },
    {
      "rank": 17,
      "name": "마이곰이",
      "viewers": "1677",
      "platform": "SOOP",
      "link": ""
    },
    {
      "rank": 18,
      "name": "하시요 HaSiyo",
      "viewers": "1600",
      "platform": "SOOP",
      "link": ""
    },
    {
      "rank": 19,
      "name": "칸_김동하",
      "viewers": "1560",
      "platform": "SOOP",
      "link": ""
    },
    {
      "rank": 20,
      "name": "우주하마",
      "viewers": "1551",
      "platform": "SOOP",
      "link": ""
    },
    {
      "rank": 1,
      "name": "저라뎃",
      "viewers": "67747",
      "platform": "SOOP",
      "link": ""
    },
    {
      "rank": 2,
      "name": "김민교.",
      "viewers": "26357",
      "platform": "SOOP",
      "link": ""
    },
    {
      "rank": 3,
      "name": "이상호",
      "viewers": "21642",
      "platform": "SOOP",
      "link": ""
    },
    {
      "rank": 4,
      "name": "박가린님[♥]",
      "viewers": "14030",
      "platform": "SOOP",
      "link": ""
    },
    {
      "rank": 5,
      "name": "우왁굳",
      "viewers": "928",
      "platform": "SOOP",
      "link": ""
    },
    {
      "rank": 6,
      "name": "윤가놈",
      "viewers": "12098",
      "platform": "SOOP",
      "link": ""
    },
    {
      "rank": 7,
      "name": "인피쉰",
      "viewers": "10566",
      "platform": "SOOP",
      "link": ""
    },
    {
      "rank": 8,
      "name": "개그팀[졸탄]",
      "viewers": "10516",
      "platform": "SOOP",
      "link": ""
    },
    {
      "rank": 9,
      "name": "fpsthailand",
      "viewers": "9294",
      "platform": "SOOP",
      "link": ""
    },
    {
      "rank": 10,
      "name": "PUBG Esports",
      "viewers": "8823",
      "platform": "SOOP",
      "link": ""
    },
    {
      "rank": 11,
      "name": "아카네 리제",
      "viewers": "8616",
      "platform": "SOOP",
      "link": ""
    },
    {
      "rank": 12,
      "name": "강지",
      "viewers": "8596",
      "platform": "SOOP",
      "link": ""
    },
    {
      "rank": 13,
      "name": "클리드1",
      "viewers": "7959",
      "platform": "SOOP",
      "link": ""
    },
    {
      "rank": 14,
      "name": "LoL멸망전",
      "viewers": "7777",
      "platform": "SOOP",
      "link": ""
    },
    {
      "rank": 15,
      "name": "두치와뿌꾸",
      "viewers": "7622",
      "platform": "SOOP",
      "link": ""
    },
    {
      "rank": 16,
      "name": "탬탬버린",
      "viewers": "7480",
      "platform": "SOOP",
      "link": ""
    },
    {
      "rank": 17,
      "name": "타요b",
      "viewers": "7204",
      "platform": "SOOP",
      "link": ""
    }
  ],
  "categories": [
    {
      "rank": 1,
      "game": "talk",
      "viewers": "21534",
      "channels": "220"
    },
    {
      "rank": 2,
      "game": "버추얼",
      "viewers": "20867",
      "channels": "160"
    },
    {
      "rank": 3,
      "game": "토크/캠방",
      "viewers": "14699",
      "channels": "165"
    },
    {
      "rank": 4,
      "game": "데드 바이 데이라이트",
      "viewers": "12592",
      "channels": "33"
    },
    {
      "rank": 5,
      "game": "스타크래프트",
      "viewers": "11979",
      "channels": "79"
    },
    {
      "rank": 6,
      "game": "리그 오브 레전드",
      "viewers": "10511",
      "channels": "157"
    },
    {
      "rank": 7,
      "game": "리그 오브 레전드",
      "viewers": "10170",
      "channels": "158"
    },
    {
      "rank": 8,
      "game": "메이플스토리",
      "viewers": "7020",
      "channels": "70"
    },
    {
      "rank": 9,
      "game": "메이플스토리",
      "viewers": "5662",
      "channels": "77"
    },
    {
      "rank": 10,
      "game": "로스트아크",
      "viewers": "4568",
      "channels": "94"
    },
    {
      "rank": 11,
      "game": "서든어택",
      "viewers": "4318",
      "channels": "266"
    },
    {
      "rank": 12,
      "game": "종합게임",
      "viewers": "4255",
      "channels": "66"
    },
    {
      "rank": 13,
      "game": "팰월드",
      "viewers": "3931",
      "channels": "111"
    },
    {
      "rank": 14,
      "game": "PUBG: 배틀그라운드",
      "viewers": "3284",
      "channels": "238"
    },
    {
      "rank": 15,
      "game": "림버스 컴퍼니",
      "viewers": "2622",
      "channels": "12"
    },
    {
      "rank": 16,
      "game": "여행",
      "viewers": "2429",
      "channels": "34"
    }
  ]
}