{
  "platforms": [
    {
      "rank": 1,
      "name": "SOOP",
      "viewers": "22769",
      "channels": "780",
      "link": "https://www.sooplive.com"
    },
    {
      "rank": 2,
      "name": "치지직",
      "viewers": "17258",
      "channels": "693",
      "link": "https://chzzk.naver.com"
    },
    {
      "rank": 3,
      "name": "트위치",
      "viewers": "1730",
      "channels": "48",
      "link": "https://www.twitch.tv"
    },
    {
      "rank": 4,
      "name": "씨미",
      "viewers": "47",
      "channels": "16",
      "link": "https://seemi.live"
    }
  ],
  "fetched": "2026-07-23T07:47:19",
  "streamers": [
    {
      "rank": 1,
      "name": "타요b",
      "viewers": "3972",
      "platform": "SOOP",
      "link": ""
    },
    {
      "rank": 2,
      "name": "아리사",
      "viewers": "2513",
      "platform": "SOOP",
      "link": ""
    },
    {
      "rank": 3,
      "name": "서새봄냥 SEBOM",
      "viewers": "2037",
      "platform": "SOOP",
      "link": ""
    },
    {
      "rank": 4,
      "name": "나나문",
      "viewers": "1137",
      "platform": "SOOP",
      "link": ""
    },
    {
      "rank": 5,
      "name": "김나성",
      "viewers": "996",
      "platform": "SOOP",
      "link": ""
    },
    {
      "rank": 6,
      "name": "수찬",
      "viewers": "995",
      "platform": "SOOP",
      "link": ""
    },
    {
      "rank": 7,
      "name": "고차비",
      "viewers": "938",
      "platform": "SOOP",
      "link": ""
    },
    {
      "rank": 8,
      "name": "정서이_",
      "viewers": "904",
      "platform": "SOOP",
      "link": ""
    },
    {
      "rank": 9,
      "name": "서도일",
      "viewers": "872",
      "platform": "SOOP",
      "link": ""
    },
    {
      "rank": 10,
      "name": "슈카슈카",
      "viewers": "690",
      "platform": "SOOP",
      "link": ""
    },
    {
      "rank": 11,
      "name": "햄쿠비",
      "viewers": "680",
      "platform": "SOOP",
      "link": ""
    },
    {
      "rank": 12,
      "name": "황원태",
      "viewers": "626",
      "platform": "SOOP",
      "link": ""
    },
    {
      "rank": 13,
      "name": "♥심장",
      "viewers": "532",
      "platform": "SOOP",
      "link": ""
    },
    {
      "rank": 14,
      "name": "히피",
      "viewers": "471",
      "platform": "SOOP",
      "link": ""
    },
    {
      "rank": 15,
      "name": "후추",
      "viewers": "447",
      "platform": "SOOP",
      "link": ""
    },
    {
      "rank": 16,
      "name": "해블린",
      "viewers": "439",
      "platform": "SOOP",
      "link": ""
    },
    {
      "rank": 17,
      "name": "우정우정우정우정",
      "viewers": "420",
      "platform": "SOOP",
      "link": ""
    },
    {
      "rank": 18,
      "name": "조디악악악",
      "viewers": "385",
      "platform": "SOOP",
      "link": ""
    },
    {
      "rank": 19,
      "name": "초그매",
      "viewers": "370",
      "platform": "SOOP",
      "link": ""
    },
    {
      "rank": 20,
      "name": "BJ로키-",
      "viewers": "346",
      "platform": "SOOP",
      "link": ""
    },
    {
      "rank": 1,
      "name": "김민교.",
      "viewers": "47537",
      "platform": "SOOP",
      "link": ""
    },
    {
      "rank": 2,
      "name": "철구형2↑",
      "viewers": "25310",
      "platform": "SOOP",
      "link": ""
    },
    {
      "rank": 3,
      "name": "FCO공식",
      "viewers": "25295",
      "platform": "SOOP",
      "link": ""
    },
    {
      "rank": 4,
      "name": "이상호",
      "viewers": "21778",
      "platform": "SOOP",
      "link": ""
    },
    {
      "rank": 5,
      "name": "항상#킴성태",
      "viewers": "20755",
      "platform": "SOOP",
      "link": ""
    },
    {
      "rank": 6,
      "name": "이스타TV",
      "viewers": "16164",
      "platform": "SOOP",
      "link": ""
    },
    {
      "rank": 7,
      "name": "랄로",
      "viewers": "13201",
      "platform": "SOOP",
      "link": ""
    },
    {
      "rank": 8,
      "name": "우왁굳",
      "viewers": "11194",
      "platform": "SOOP",
      "link": ""
    },
    {
      "rank": 9,
      "name": "인피쉰",
      "viewers": "10415",
      "platform": "SOOP",
      "link": ""
    },
    {
      "rank": 10,
      "name": "따효니",
      "viewers": "9951",
      "platform": "SOOP",
      "link": ""
    },
    {
      "rank": 11,
      "name": "저라뎃",
      "viewers": "9010",
      "platform": "SOOP",
      "link": ""
    },
    {
      "rank": 12,
      "name": "클리드1",
      "viewers": "8377",
      "platform": "SOOP",
      "link": ""
    },
    {
      "rank": 13,
      "name": "강만식",
      "viewers": "8262",
      "platform": "SOOP",
      "link": ""
    },
    {
      "rank": 14,
      "name": "남순",
      "viewers": "7799",
      "platform": "SOOP",
      "link": ""
    },
    {
      "rank": 15,
      "name": "침착맨 원본 박물관",
      "viewers": "7602",
      "platform": "SOOP",
      "link": ""
    },
    {
      "rank": 16,
      "name": "PUBG Esports",
      "viewers": "7324",
      "platform": "SOOP",
      "link": ""
    },
    {
      "rank": 17,
      "name": "괴물쥐",
      "viewers": "7212",
      "platform": "SOOP",
      "link": ""
    },
    {
      "name": "메타용",
      "viewers": 87,
      "category": "로스트아크",
      "title": "장난감이 고장났어요 / 룰렛, 영도 상시 오픈",
      "platform": "치지직",
      "link": "https://chzzk.naver.com/live/20130986"
    },
    {
      "name": "김호러",
      "viewers": 78,
      "category": "로스트아크",
      "title": "[쌩모코코] 제가 고른 캐릭터들이 다 너프됐어요",
      "platform": "치지직",
      "link": "https://chzzk.naver.com/live/20132312"
    },
    {
      "name": "전홀리",
      "viewers": 71,
      "category": "오버워치",
      "title": "술 담배 그리고 그륩",
      "platform": "치지직",
      "link": "https://chzzk.naver.com/live/20135260"
    },
    {
      "name": "달빛머무는밤",
      "viewers": 67,
      "category": "로스트아크",
      "title": "응..패싱에 너프구나",
      "platform": "치지직",
      "link": "https://chzzk.naver.com/live/20130053"
    },
    {
      "name": "이차가식기전에",
      "viewers": 56,
      "category": "롤",
      "title": "C1 2346 이차식 랭킹 1위 가볼까 / 관피, 롤재판 가능",
      "platform": "치지직",
      "link": "https://chzzk.naver.com/live/20135365"
    },
    {
      "name": "리연 L",
      "viewers": 50,
      "category": "로스트아크",
      "title": "노방종 57일차 -완- 자는중... 달소 1.2+ 금손호소인 빌드 연구 ",
      "platform": "치지직",
      "link": "https://chzzk.naver.com/live/20118161"
    },
    {
      "name": "김준민1",
      "viewers": 44,
      "category": "게임",
      "title": "랭킹1등 놀이 Chpater.2 : 부캐 랭킹2등 찍기 ",
      "platform": "치지직",
      "link": "https://chzzk.naver.com/live/20133292"
    },
    {
      "name": "홍차 Redtea",
      "viewers": 39,
      "category": "게임",
      "title": "오늘은 악사, 사제입니다",
      "platform": "치지직",
      "link": "https://chzzk.naver.com/live/20135607"
    },
    {
      "name": "람보람1",
      "viewers": 33,
      "category": "오버워치",
      "title": "맞짱까실분;",
      "platform": "치지직",
      "link": "https://chzzk.naver.com/live/20134067"
    },
    {
      "name": "루 니",
      "viewers": 27,
      "category": "로스트아크",
      "title": "두번째 캐릭터 정하기  !굿즈 !보컬렛",
      "platform": "치지직",
      "link": "https://chzzk.naver.com/live/20134802"
    },
    {
      "name": "난 슬플때 풀캠을 돌아",
      "viewers": 24,
      "category": "롤",
      "title": "롤 클래식 요양원",
      "platform": "치지직",
      "link": "https://chzzk.naver.com/live/20135703"
    },
    {
      "name": "Uann 유안",
      "viewers": 22,
      "category": "오버워치",
      "title": "아침큐",
      "platform": "치지직",
      "link": "https://chzzk.naver.com/live/20135702"
    },
    {
      "name": "김태호a",
      "viewers": 20,
      "category": "게임",
      "title": "c1128점 시작 1400점 40만원 미션",
      "platform": "치지직",
      "link": "https://chzzk.naver.com/live/20131046"
    },
    {
      "name": "도 마 도",
      "viewers": 19,
      "category": "오버워치",
      "title": "도마도는 다이아가 딱이야",
      "platform": "치지직",
      "link": "https://chzzk.naver.com/live/20130647"
    },
    {
      "name": "wkdrbwls",
      "viewers": 18,
      "category": "오버워치",
      "title": "gd",
      "platform": "치지직",
      "link": "https://chzzk.naver.com/live/20135334"
    },
    {
      "name": "순두둥",
      "viewers": 18,
      "category": "배틀그라운드",
      "title": "[!룰렛][시참][유입환영] 1부_성세천하 2 / 2부_배그둥(미성년자x",
      "platform": "치지직",
      "link": "https://chzzk.naver.com/live/20132788"
    },
    {
      "name": "유설Seol",
      "viewers": 17,
      "category": "발로란트",
      "title": "꾸준하게 망가진 생활패턴",
      "platform": "치지직",
      "link": "https://chzzk.naver.com/live/20135351"
    },
    {
      "name": "리네양",
      "viewers": 17,
      "category": "오버워치",
      "title": "패배추세 극복하기 ㅠ.ㅠ",
      "platform": "치지직",
      "link": "https://chzzk.naver.com/live/20133913"
    },
    {
      "name": "시스네",
      "viewers": 16,
      "category": "게임",
      "title": "[45일/설립자 구해요] 팔로우하면 둘 굴려드립니다",
      "platform": "치지직",
      "link": "https://chzzk.naver.com/live/20131386"
    },
    {
      "name": "냥냥꽁냥쫑냥",
      "viewers": 16,
      "category": "발로란트",
      "title": "평화로운 발로란트 하기",
      "platform": "치지직",
      "link": "https://chzzk.naver.com/live/20135047"
    },
    {
      "name": "삭초이",
      "viewers": 15,
      "category": "게임",
      "title": "안녕?",
      "platform": "치지직",
      "link": "https://chzzk.naver.com/live/20133027"
    },
    {
      "name": "공갈",
      "viewers": 15,
      "category": "마인크래프트",
      "title": "초기화 스타팅",
      "platform": "치지직",
      "link": "https://chzzk.naver.com/live/20131031"
    },
    {
      "name": "린 화",
      "viewers": 15,
      "category": "로스트아크",
      "title": "비 론나오는데 출근해..? 진짜? ㅘ.. 진짜.. 와.. 비 론나오는데 ",
      "platform": "치지직",
      "link": "https://chzzk.naver.com/live/20135666"
    },
    {
      "name": "나쁜악마",
      "viewers": 14,
      "category": "롤",
      "title": "심심",
      "platform": "치지직",
      "link": "https://chzzk.naver.com/live/20134360"
    },
    {
      "name": "폴탄poltan",
      "viewers": 14,
      "category": "발로란트",
      "title": "2?",
      "platform": "치지직",
      "link": "https://chzzk.naver.com/live/20135376"
    },
    {
      "name": "웆ㅜ",
      "viewers": 13,
      "category": "게임",
      "title": "데르따뽀쓰 ! 두둥-탁🎶",
      "platform": "치지직",
      "link": "https://chzzk.naver.com/live/20130808"
    },
    {
      "name": "도르밍",
      "viewers": 13,
      "category": "발로란트",
      "title": "[누나 목소리] 듀오권이 안 끝나요ㅜㅡㅜㅠㅠㅜㅜㅜ 방종을 못해요 ㅜㅜㅗㅠ",
      "platform": "치지직",
      "link": "https://chzzk.naver.com/live/20127896"
    },
    {
      "name": "나는기룡",
      "viewers": 12,
      "category": "발로란트",
      "title": "흑룡 흘룡",
      "platform": "치지직",
      "link": "https://chzzk.naver.com/live/20134638"
    },
    {
      "name": "진짜진진",
      "viewers": 12,
      "category": "배틀그라운드",
      "title": "평딜 150의 길 (시참가능)",
      "platform": "치지직",
      "link": "https://chzzk.naver.com/live/20132133"
    },
    {
      "name": "핸떠기",
      "viewers": 12,
      "category": "로스트아크",
      "title": "노방종 14일차 마무리",
      "platform": "치지직",
      "link": "https://chzzk.naver.com/live/20118769"
    },
    {
      "name": "마스카 masca",
      "viewers": 11,
      "category": "게임",
      "title": "전장 기회 다섯번 주겠다",
      "platform": "치지직",
      "link": "https://chzzk.naver.com/live/20135575"
    },
    {
      "name": "풀보이",
      "viewers": 11,
      "category": "배틀그라운드",
      "title": "반갑습니다",
      "platform": "치지직",
      "link": "https://chzzk.naver.com/live/20133168"
    },
    {
      "name": "이냐미",
      "viewers": 11,
      "category": "로스트아크",
      "title": "스펙업 힘드렁",
      "platform": "치지직",
      "link": "https://chzzk.naver.com/live/20135201"
    },
    {
      "name": "NaDa이윤열",
      "viewers": 11,
      "category": "스타크래프트",
      "title": "이윤열의 스타방송 2026-07-23(목) 아침 ★생방송★",
      "platform": "치지직",
      "link": "https://chzzk.naver.com/live/20135744"
    },
    {
      "name": "C1 Karen",
      "viewers": 10,
      "category": "롤",
      "title": "C1카렌 / 배치부터 챌까지미션,투챌가즈앗 / 롤재판O / 강의,관피o",
      "platform": "치지직",
      "link": "https://chzzk.naver.com/live/19993879"
    },
    {
      "name": "줴이기호",
      "viewers": 10,
      "category": "롤",
      "title": "솔랭전사플래도전기",
      "platform": "치지직",
      "link": "https://chzzk.naver.com/live/20133766"
    },
    {
      "name": "짱모띠",
      "viewers": 10,
      "category": "배틀그라운드",
      "title": "배그❤️띠띠빵빵 경댕뎡",
      "platform": "치지직",
      "link": "https://chzzk.naver.com/live/20134033"
    },
    {
      "name": "과학잡지",
      "viewers": 9,
      "category": "오버워치",
      "title": "오버워치 플레의 오늘은 화를 내지 않을려고 했는데 OBS 32.2 업데이",
      "platform": "치지직",
      "link": "https://chzzk.naver.com/live/20135412"
    },
    {
      "name": "마료Maryo",
      "viewers": 9,
      "category": "로스트아크",
      "title": "내 부두술이 정상화를 가져왔다 / 랏소서 와쪄염",
      "platform": "치지직",
      "link": "https://chzzk.naver.com/live/20133970"
    },
    {
      "name": "냔땐구",
      "viewers": 9,
      "category": "스타크래프트",
      "title": "2300... 찍어야한다 ",
      "platform": "치지직",
      "link": "https://chzzk.naver.com/live/20135306"
    },
    {
      "name": "히미카 스이",
      "viewers": 8,
      "category": "발로란트",
      "title": "자버림 청년...",
      "platform": "치지직",
      "link": "https://chzzk.naver.com/live/20130760"
    },
    {
      "name": "콜라희",
      "viewers": 8,
      "category": "배틀그라운드",
      "title": "[2부] 배그즐겜/ 킬룰렛 얼마 안남았다!!!!!!! [1부] 드디어 그",
      "platform": "치지직",
      "link": "https://chzzk.naver.com/live/20131242"
    },
    {
      "name": "혼 광",
      "viewers": 8,
      "category": "로스트아크",
      "title": "[카단섭/!노방종] 레이드 가자",
      "platform": "치지직",
      "link": "https://chzzk.naver.com/live/20123331"
    },
    {
      "name": "셀레니 Seleni",
      "viewers": 7,
      "category": "게임",
      "title": "명조: 어려워도 예쁜 언니들 보려고 한다",
      "platform": "치지직",
      "link": "https://chzzk.naver.com/live/20135637"
    },
    {
      "name": "와킨",
      "viewers": 7,
      "category": "게임",
      "title": "일찍 일어나는 벌레가 잡아먹힌다  [맞팔]",
      "platform": "치지직",
      "link": "https://chzzk.naver.com/live/20135572"
    },
    {
      "name": "쿠로이시로네코",
      "viewers": 7,
      "category": "롤",
      "title": "모닝롤",
      "platform": "치지직",
      "link": "https://chzzk.naver.com/live/20135582"
    },
    {
      "name": "김헨리",
      "viewers": 7,
      "category": "로스트아크",
      "title": "찐뉴비) 로아 4일차 레이드 4막 싱글 켠왕!",
      "platform": "치지직",
      "link": "https://chzzk.naver.com/live/20128489"
    },
    {
      "name": "소주의요정",
      "viewers": 7,
      "category": "스타크래프트",
      "title": "넥서스도 300원 해줘",
      "platform": "치지직",
      "link": "https://chzzk.naver.com/live/20134957"
    },
    {
      "name": "해나Hannah",
      "viewers": 6,
      "category": "배틀그라운드",
      "title": "배그~~인데 사녹만 하는",
      "platform": "치지직",
      "link": "https://chzzk.naver.com/live/20135008"
    },
    {
      "name": "아가엄마슈비",
      "viewers": 6,
      "category": "마인크래프트",
      "title": "[롤링섭] 잠자기전 템포 선릿밸리",
      "platform": "치지직",
      "link": "https://chzzk.naver.com/live/20135601"
    }
  ],
  "categories": [
    {
      "rank": 1,
      "game": "종합게임",
      "viewers": "4214",
      "channels": "41"
    },
    {
      "rank": 2,
      "game": "talk",
      "viewers": "2873",
      "channels": "86"
    },
    {
      "rank": 3,
      "game": "버추얼",
      "viewers": "2754",
      "channels": "55"
    },
    {
      "rank": 4,
      "game": "다크 소울 3",
      "viewers": "2513",
      "channels": "1"
    },
    {
      "rank": 5,
      "game": "토크/캠방",
      "viewers": "2220",
      "channels": "67"
    },
    {
      "rank": 6,
      "game": "팰월드",
      "viewers": "2145",
      "channels": "36"
    },
    {
      "rank": 7,
      "game": "리그 오브 레전드",
      "viewers": "2104",
      "channels": "72"
    },
    {
      "rank": 8,
      "game": "붕괴: 스타레일",
      "viewers": "2037",
      "channels": "1"
    },
    {
      "rank": 9,
      "game": "Just Chatting",
      "viewers": "1592",
      "channels": "11"
    },
    {
      "rank": 10,
      "game": "PUBG: 배틀그라운드",
      "viewers": "1501",
      "channels": "95"
    },
    {
      "rank": 11,
      "game": "음악 스트리밍",
      "viewers": "1309",
      "channels": "46"
    },
    {
      "rank": 12,
      "game": "메이플스토리 월드",
      "viewers": "1209",
      "channels": "13"
    },
    {
      "rank": 13,
      "game": "이스케이프 프롬 타르코프",
      "viewers": "1088",
      "channels": "9"
    },
    {
      "rank": 14,
      "game": "델타포스",
      "viewers": "976",
      "channels": "9"
    },
    {
      "rank": 15,
      "game": "음악/노래",
      "viewers": "905",
      "channels": "33"
    },
    {
      "rank": 16,
      "game": "음악 라이브",
      "viewers": "705",
      "channels": "12"
    }
  ]
}